cs/ndjson.py
cs_ndjson-20250528.dist-info/WHEEL
cs_ndjson-20250528.dist-info/METADATA
cs_ndjson-20250528.dist-info/RECORD
